MANIFEST.in
README.txt
bootstrap.py
buildout.cfg
setup.cfg
setup.py
docs/HISTORY.txt
docs/INSTALL.txt
docs/LICENSE.GPL
docs/LICENSE.txt
fourdigits/__init__.py
fourdigits.chosen.egg-info/PKG-INFO
fourdigits.chosen.egg-info/SOURCES.txt
fourdigits.chosen.egg-info/dependency_links.txt
fourdigits.chosen.egg-info/entry_points.txt
fourdigits.chosen.egg-info/namespace_packages.txt
fourdigits.chosen.egg-info/not-zip-safe
fourdigits.chosen.egg-info/paster_plugins.txt
fourdigits.chosen.egg-info/requires.txt
fourdigits.chosen.egg-info/top_level.txt
fourdigits/chosen/__init__.py
fourdigits/chosen/configure.zcml
fourdigits/chosen/tests.py
fourdigits/chosen/profiles/default/cssregistry.xml
fourdigits/chosen/profiles/default/jsregistry.xml
fourdigits/chosen/profiles/default/metadata.xml
fourdigits/chosen/static/main.css
fourdigits/chosen/static/main.js
fourdigits/chosen/static/chosen/chosen-sprite.png
fourdigits/chosen/static/chosen/chosen.css
fourdigits/chosen/static/chosen/chosen.dev.js
fourdigits/chosen/static/chosen/chosen.min.js