Metadata-Version: 1.0
Name: fourdigits.chosen
Version: 0.4
Summary: Integrates the Chosen javascript library in Plone
Home-page: https://github.com/jaroel/fourdigits.chosen/
Author: Roel Bruggink
Author-email: roel@jaroel.nl
License: GPL
Platform: UNKNOWN
Classifier: Framework :: Plone
Classifier: Programming Language :: Python
Classifier: Programming Language :: JavaScript
